setup.cfg
setup.py
dumbserver/__init__.py
dumbserver/arguments.py
dumbserver/configreader.py
dumbserver/constants.py
dumbserver/expectations.py
dumbserver/treelib_adapter.py
dumbserver.egg-info/PKG-INFO
dumbserver.egg-info/SOURCES.txt
dumbserver.egg-info/dependency_links.txt
dumbserver.egg-info/requires.txt
dumbserver.egg-info/top_level.txt
twisted/plugins/dumbserver_plugin.py