Metadata-Version: 1.1
Name: dumbserver
Version: 1.0
Summary: Mock several REST services in one go!
Home-page: https://github.com/varunmulloli/dumbserver
Author: Varun Mulloli
Author-email: mulloli@me.com
License: MIT
Download-URL: https://github.com/varunmulloli/dumbserver/tarball/1.0
Keywords: mockserver,mock server,service,http,REST
Platform: UNKNOWN
Classifier: Development Status :: 3 - Alpha
Classifier: Environment :: Web Environment
Classifier: Framework :: Twisted
Classifier: Intended Audience :: Developers
Classifier: License :: OSI Approved :: MIT License
Classifier: Natural Language :: English
Classifier: Operating System :: Unix
Classifier: Programming Language :: Python :: 2.7
Classifier: Topic :: Software Development :: Quality Assurance
Classifier: Topic :: Software Development :: Testing
